{
  "idActivite": "36",
  "idParcours": "0",
  "nom": "Y a-t-il du sucre partout ?",
  "state": "INPROGRESS",
  "duration": 15,
  "startedAt": 0,
  "finishedAt": 0,
  "reviewAt": 0,
  "entries": [
    {
      "position": 0,
      "question": "",
      "documents": [],
      "typeRendu": "qcm",
      "rendu": "[{\"question\": \"Quantité de sucre dans 33cL de Coca :\", \"reponses\": {\"3,5 morceaux de sucre\": false, \"7 morceaux de sucre\": false, \"0,5 morceaux de sucre\": false, \"1 morceau de sucre\": false}}, {\"question\": \"Quantité de sucre dans 1 cuillère à soupe de ketchup :\", \"reponses\": {\"3,5 morceaux de sucre\": false, \"7 morceaux de sucre\": false, \"0,5 morceaux de sucre\": false, \"1 morceau de sucre\": false}}, {\"question\": \"Quantité de sucre dans 100mL de lait :\", \"reponses\": {\"3,5 morceaux de sucre\": false, \"7 morceaux de sucre\": false, \"0,5 morceaux de sucre\": false, \"1 morceau de sucre\": false}}, {\"question\": \"Quantité de sucre dans 100g de gâteau granola :\", \"reponses\": {\"3,5 morceaux de sucre\": false, \"7 morceaux de sucre\": false, \"0,5 morceaux de sucre\": false, \"1 morceau de sucre\": false}}, {\"question\": \"Quantité de sucre dans 100g de chocolat en poudre :\", \"reponses\": {\"6 morceaux de sucre\": false, \"0 morceaux de sucre\": false, \"13,5 morceaux de sucre\": false, \"1,5 morceau de sucre\": false}}, {\"question\": \"Quantité de sucre dans 100g de jus d’orange :\", \"reponses\": {\"6 morceaux de sucre\": false, \"0 morceaux de sucre\": false, \"13,5 morceaux de sucre\": false, \"1,5 morceau de sucre\": false}}, {\"question\": \"Quantité de sucre dans 100g de miel pops :\", \"reponses\": {\"6 morceaux de sucre\": false, \"0 morceaux de sucre\": false, \"13,5 morceaux de sucre\": false, \"1,5 morceau de sucre\": false}}, {\"question\": \"Quantité de sucre dans 5 tranches de pain de mie :\", \"reponses\": {\"6 morceaux de sucre\": false, \"0 morceaux de sucre\": false, \"13,5 morceaux de sucre\": false, \"1,5 morceau de sucre\": false}}, {\"question\": \"Parmi les propositions suivantes, quels termes désignent le sucre sur les étiquettes alimentaires (2 bonnes réponses) ?\", \"reponses\": {\"Amidon\": false, \"Curcumine\": false, \"Acide ascorbique\": false, \"Sirop de glucose\": false}}, {\"question\": \"Parmi les propositions suivantes, quels termes désignent le sucre sur les étiquettes alimentaires (2 bonnes réponses) ?\", \"reponses\": {\"Malt d’orge\": false, \"Sirop de fructose\": false, \"Carbonates d’ammonium\": false, \"Sulfate de zinc\": false}}]",
      "state": "NOTSTARTED",
      "tracked": true,
      "page": 1
    },
    {
      "position": 2,
      "question": "Envoie nous la photo de l’aliment contenant le plus de sucre que tu es chez toi puis répond à cette petite question !",
      "documents": [],
      "typeRendu": "file",
      "rendu": "",
      "state": "NOTSTARTED",
      "tracked": true,
      "page": 2
    },
    {
      "position": 3,
      "question": "Au vu du nombre de sucre dans les aliments que tu a vu plus haut et du nombre d'appellations différentes du sucre sur les étiquettes, donne nous une alternative que tu pourrais mettre en place dans ta vie de tous les jours et/ou ta vie scoute pour réduire ta consommation de sucre.",
      "documents": [],
      "typeRendu": "text",
      "rendu": "",
      "state": "NOTSTARTED",
      "tracked": true,
      "page": 2
    }
  ]
}