{
  "idActivite": "7",
  "idParcours": "1",
  "state": "INPROGRESS",
  "duration": 10,
  "startedAt": 0,
  "finishedAt": 0,
  "reviewAt": 0,
  "entries": [
    {
      "position": 0,
      "question": "Réponds aux questions suivantes",
      "documents": [],
      "typeRendu": "orderList",
      "rendu": "[{'question': 'Quelle étape permet de gagner du temps pendant la préparation du repas ?', 'reponses': ['Sortir le matériel', 'Maintenir le plat au chaud', 'Nettoyer la vaisselle et le plan de travail', 'Éplucher']}, {'question': 'Quelle étape peut permettre d’éviter des accident liés à la cuisine ?', 'reponses': ['Maintenir le plat au chaud', 'Éplucher', 'Laver les aliments qui le nécessitent', 'Organiser son plan de travail']}, {'question': 'Quelle étape de la préparation du repas permet de respecter les règles d’hygiène ?', 'reponses': ['Découper, râper, rincer', 'Servir', 'Se laver les mains', 'Organiser son plan de travail']}, {'question': 'Quelle étape n’est pas nécessaire pour la préparation de tous les plats ?', 'reponses': ['Se laver les mains', 'Lancer la cuisson', 'Servir', 'Sortir le matériel']}, {'question': 'Que doit-on faire avant de commencer à éplucher ou couper les aliments ?', 'reponses': ['Egoutter', 'Surveiller la cuisson', 'Nettoyer la vaisselle et le plan de travail', 'Laver les ingrédients qui le nécessitent']}, {'question': 'Quelle est la dernière étape de la préparation du repas que les scouts rechignent toujours à faire ?', 'reponses': ['Se laver les mains', 'Nettoyer la vaisselle et le plan de travail', 'Servir', 'Surveiller la cuisson']}, {'question': 'Quelle étape permet d’éviter que le plat soit trop liquide ?', 'reponses': ['Surveiller la cuisson', 'Laver les ingrédients qui le nécessitent', 'Egoutter', 'Eplucher']}, {'question': 'Quelle étape permet d’enlever les parties inutiles ou mauvaises d’un légume ?', 'reponses': ['Eplucher', 'Nettoyer la vaisselle et le plan de travail', 'Servir', 'Sortir le matériel']}, {'question': 'Que faut-il faire après avoir lancer la cuisson des aliments ?', 'reponses': ['Aller faire la sieste', 'Maintenir au chaud', 'Surveiller la cuisson', 'Se laver les mains']}, {'question': 'Quelle étape nécessite de rester debout quand tout le monde est assis ?', 'reponses': ['Surveiller la cuisson', 'Découper, râper, rincer', 'Sortir le matériel', 'Servir']}, {'question': 'Comment vérifier qu’il ne manque rien pour préparer le plat ?', 'reponses': ['Sortir les ingrédients dans l’ordre de préparation', 'Surveiller la cuisson', 'Servir', 'Découper, râper, rincer']}, {'question': 'Quelle étape permet de choisir la présentation du plat ?', 'reponses': ['Surveiller la cuisson', 'Organiser son plan de travail', 'Découper, râper, rincer', 'Maintenir au chaud']}, {'question': 'Quelle étape est nécessaire quand un plat est préparé à l’avance ?', 'reponses': ['Se laver les mains', 'Maintenir au chaud', 'Organiser son plan de travail', 'Servir']}]",
      "state": "NOTSTARTED",
      "tracked": true,
      "page": 1
    }
  ]
}